[
    {
        "Pub": ["Chinese"],
        "LogoGrp": "8C Generic Pix Chinese Clr",
        "Charges": ["Chargeable"],
        "Colour": ["Colour"]
    },
    {
        "Pub": ["Chinese"],
        "LogoGrp": "8C Prop Pix01 P18",
        "Charges": ["Chargeable"],
        "Colour": ["Colour"]
    },
    {
        "Pub": ["Chinese"],
        "LogoGrp": "8C Prop Pix Chinese",
        "Charges": ["Chargeable"],
        "Colour": ["B&W"]
    },
    {
        "Pub": ["Chinese"],
        "LogoGrp": "8C Prop Pix Chinese Clr",
        "Charges": ["Chargeable"],
        "Colour": ["Colour"]
    },
    {
        "Pub": ["Chinese"],
        "LogoGrp": "8C Veh Pix01 V08",
        "Charges": ["Chargeable"],
        "Colour": ["Colour"]
    },
    {
        "Pub": ["Chinese"],
        "LogoGrp": "8C Vehicle Pix Chinese",
        "Charges": ["Chargeable"],
        "Colour": ["B&W"]
    },
    {
        "Pub": ["Chinese"],
        "LogoGrp": "8C Vehicle Pix Chinese Clr",
        "Charges": ["Chargeable"],
        "Colour": ["Colour"]
    },
    {
        "Pub": ["Chinese"],
        "LogoGrp": "Carnival",
        "Charges": ["Non-Chargeable"],
        "Colour": ["B&W"]
    },
    {
        "Pub": ["Chinese"],
        "LogoGrp": "Carnival",
        "Charges": ["Non-Chargeable"],
        "Colour": ["Colour"]
    },
    {
        "Pub": ["Chinese"],
        "LogoGrp": "Co Logo Chinese Clr",
        "Charges": ["Chargeable"],
        "Colour": ["Colour"]
    },
    {
        "Pub": ["Chinese"],
        "LogoGrp": "Display Ad Components",
        "Charges": ["Non-Chargeable"],
        "Colour": ["B&W"]
    },
    {
        "Pub": ["Chinese"],
        "LogoGrp": "Generic Pix Chinese Clr",
        "Charges": ["Chargeable"],
        "Colour": ["Colour"]
    },
    {
        "Pub": ["Chinese"],
        "LogoGrp": "Prop Pix",
        "Charges": ["Chargeable"],
        "Colour": ["B&W"]
    },
    {
        "Pub": ["Chinese"],
        "LogoGrp": "Prop Pix Chinese",
        "Charges": ["Chargeable"],
        "Colour": ["B&W"]
    },
    {
        "Pub": ["Chinese"],
        "LogoGrp": "Prop Pix Chinese Clr",
        "Charges": ["Chargeable"],
        "Colour": ["Colour"]
    },
    {
        "Pub": ["Chinese"],
        "LogoGrp": "Prop Pix Clr Sun",
        "Charges": ["Chargeable"],
        "Colour": ["Colour"]
    },
    {
        "Pub": ["Chinese"],
        "LogoGrp": "SGD8 Veh02 V08",
        "Charges": ["Chargeable"],
        "Colour": ["Colour"]
    },
    {
        "Pub": ["Chinese"],
        "LogoGrp": "Vehicle Pix",
        "Charges": ["Chargeable"],
        "Colour": ["B&W"]
    },
    {
        "Pub": ["Chinese"],
        "LogoGrp": "Vehicle Pix Chinese",
        "Charges": ["Chargeable"],
        "Colour": ["B&W"]
    },
    {
        "Pub": ["Chinese"],
        "LogoGrp": "Vehicle Pix Chinese Clr",
        "Charges": ["Chargeable"],
        "Colour": ["Colour"]
    },
    {
        "Pub": ["Chinese"],
        "LogoGrp": "Vehicle Pix Clr Sun",
        "Charges": ["Chargeable"],
        "Colour": ["Colour"]
    },
    {
        "Pub": ["Chinese"],
        "LogoGrp": "zVAC PPSL Car Pix",
        "Charges": ["Chargeable"],
        "Colour": ["Colour"]
    },
    {
        "Pub": ["English"],
        "LogoGrp": "8C Generic Pix English Clr",
        "Charges": ["Chargeable"],
        "Colour": ["Colour"]
    },
    {
        "Pub": ["English"],
        "LogoGrp": "8C Generic Pix Malay Clr",
        "Charges": ["Chargeable"],
        "Colour": ["Colour"]
    },
    {
        "Pub": ["English"],
        "LogoGrp": "8C Prop Pix01 P18",
        "Charges": ["Chargeable"],
        "Colour": ["Colour"]
    },
    {
        "Pub": ["English"],
        "LogoGrp": "8C Prop Pix Clr Sun",
        "Charges": ["Chargeable"],
        "Colour": ["Colour"]
    },
    {
        "Pub": ["English"],
        "LogoGrp": "8C Prop Pix English Clr",
        "Charges": ["Chargeable"],
        "Colour": ["Colour"]
    },
    {
        "Pub": ["English"],
        "LogoGrp": "8C Veh FOC Dealers Tag",
        "Charges": ["Non-Chargeable"],
        "Colour": ["B&W"]
    },
    {
        "Pub": ["English"],
        "LogoGrp": "8C Veh Pix01 V08",
        "Charges": ["Chargeable"],
        "Colour": ["Colour"]
    },
    {
        "Pub": ["English"],
        "LogoGrp": "8C Veh Pix Clr Sun",
        "Charges": ["Chargeable"],
        "Colour": ["Colour"]
    },
    {
        "Pub": ["English"],
        "LogoGrp": "8C Veh Pix English Clr",
        "Charges": ["Chargeable"],
        "Colour": ["Colour"]
    },
    {
        "Pub": ["English"],
        "LogoGrp": "Carnival",
        "Charges": ["Non-Chargeable"],
        "Colour": ["B&W"]
    },
    {
        "Pub": ["English"],
        "LogoGrp": "Carnival",
        "Charges": ["Non-Chargeable"],
        "Colour": ["Colour"]
    },
    {
        "Pub": ["English"],
        "LogoGrp": "Co Logo English Clr",
        "Charges": ["Chargeable"],
        "Colour": ["Colour"]
    },
    {
        "Pub": ["English"],
        "LogoGrp": "Co Logo Malay Clr",
        "Charges": ["Chargeable"],
        "Colour": ["Colour"]
    },
    {
        "Pub": ["English"],
        "LogoGrp": "Display Ad Components",
        "Charges": ["Non-Chargeable"],
        "Colour": ["B&W"]
    },
    {
        "Pub": ["English"],
        "LogoGrp": "Generic Pix English Clr",
        "Charges": ["Chargeable"],
        "Colour": ["Colour"]
    },
    {
        "Pub": ["English"],
        "LogoGrp": "Generic Pix Malay Clr",
        "Charges": ["Chargeable"],
        "Colour": ["Colour"]
    },
    {
        "Pub": ["English"],
        "LogoGrp": "Prop Pix",
        "Charges": ["Chargeable"],
        "Colour": ["B&W"]
    },
    {
        "Pub": ["English"],
        "LogoGrp": "Prop Pix Clr Sun",
        "Charges": ["Chargeable"],
        "Colour": ["Colour"]
    },
    {
        "Pub": ["English"],
        "LogoGrp": "Prop Pix English Clr",
        "Charges": ["Chargeable"],
        "Colour": ["Colour"]
    },
    {
        "Pub": ["English"],
        "LogoGrp": "Prop Pix Malay",
        "Charges": ["Chargeable"],
        "Colour": ["B&W"]
    },
    {
        "Pub": ["English"],
        "LogoGrp": "Prop Pix Malay Clr",
        "Charges": ["Chargeable"],
        "Colour": ["Colour"]
    },
    {
        "Pub": ["English"],
        "LogoGrp": "SGD18 Prop02 P18",
        "Charges": ["Chargeable"],
        "Colour": ["Colour"]
    },
    {
        "Pub": ["English"],
        "LogoGrp": "SGD8 Veh02 V08",
        "Charges": ["Chargeable"],
        "Colour": ["Colour"]
    },
    {
        "Pub": ["English"],
        "LogoGrp": "Vehicle Pix",
        "Charges": ["Chargeable"],
        "Colour": ["B&W"]
    },
    {
        "Pub": ["English"],
        "LogoGrp": "Vehicle Pix Clr Sun",
        "Charges": ["Chargeable"],
        "Colour": ["Colour"]
    },
    {
        "Pub": ["English"],
        "LogoGrp": "Vehicle Pix English Clr",
        "Charges": ["Chargeable"],
        "Colour": ["Colour"]
    },
    {
        "Pub": ["English"],
        "LogoGrp": "Vehicle Pix Malay",
        "Charges": ["Chargeable"],
        "Colour": ["B&W"]
    },
    {
        "Pub": ["English"],
        "LogoGrp": "Vehicle Pix Malay Clr",
        "Charges": ["Chargeable"],
        "Colour": ["Colour"]
    },
    {
        "Pub": ["English"],
        "LogoGrp": "zVAC PPSL Car Pix",
        "Charges": ["Chargeable"],
        "Colour": ["Colour"]
    }
]